Classfile /mnt/c/project/ConcurrentInAction/lock/target/classes/me/caofeng/lock/SynchronizedMethod.class
  Last modified Aug 23, 2021; size 537 bytes
  MD5 checksum eaf1c76dee4a10ed45709b8668a716ca
  Compiled from "SynchronizedMethod.java"
public class me.caofeng.lock.SynchronizedMethod
  minor version: 0
  major version: 49
  flags: ACC_PUBLIC, ACC_SUPER
Constant pool:
   #1 = Methodref          #6.#17         // java/lang/Object."<init>":()V
   #2 = Fieldref           #18.#19        // java/lang/System.out:Ljava/io/PrintStream;
   #3 = String             #20            // Hello World
   #4 = Methodref          #21.#22        // java/io/PrintStream.println:(Ljava/lang/String;)V
   #5 = Class              #23            // me/caofeng/lock/SynchronizedMethod
   #6 = Class              #24            // java/lang/Object
   #7 = Utf8               <init>
   #8 = Utf8               ()V
   #9 = Utf8               Code
  #10 = Utf8               LineNumberTable
  #11 = Utf8               LocalVariableTable
  #12 = Utf8               this
  #13 = Utf8               Lme/caofeng/lock/SynchronizedMethod;
  #14 = Utf8               method
  #15 = Utf8               SourceFile
  #16 = Utf8               SynchronizedMethod.java
  #17 = NameAndType        #7:#8          // "<init>":()V
  #18 = Class              #25            // java/lang/System
  #19 = NameAndType        #26:#27        // out:Ljava/io/PrintStream;
  #20 = Utf8               Hello World
  #21 = Class              #28            // java/io/PrintStream
  #22 = NameAndType        #29:#30        // println:(Ljava/lang/String;)V
  #23 = Utf8               me/caofeng/lock/SynchronizedMethod
  #24 = Utf8               java/lang/Object
  #25 = Utf8               java/lang/System
  #26 = Utf8               out
  #27 = Utf8               Ljava/io/PrintStream;
  #28 = Utf8               java/io/PrintStream
  #29 = Utf8               println
  #30 = Utf8               (Ljava/lang/String;)V
{
  public me.caofeng.lock.SynchronizedMethod();
    descriptor: ()V
    flags: ACC_PUBLIC
    Code:
      stack=1, locals=1, args_size=1
         0: aload_0
         1: invokespecial #1                  // Method java/lang/Object."<init>":()V
         4: return
      LineNumberTable:
        line 3: 0
      LocalVariableTable:
        Start  Length  Slot  Name   Signature
            0       5     0  this   Lme/caofeng/lock/SynchronizedMethod;

  public synchronized void method();
    descriptor: ()V
    flags: ACC_PUBLIC, ACC_SYNCHRONIZED
    Code:
      stack=2, locals=1, args_size=1
         0: getstatic     #2                  // Field java/lang/System.out:Ljava/io/PrintStream;
         3: ldc           #3                  // String Hello World
         5: invokevirtual #4                  // Method java/io/PrintStream.println:(Ljava/lang/String;)V
         8: return
      LineNumberTable:
        line 5: 0
        line 6: 8
      LocalVariableTable:
        Start  Length  Slot  Name   Signature
            0       9     0  this   Lme/caofeng/lock/SynchronizedMethod;
}
SourceFile: "SynchronizedMethod.java"
